notifications_sender/__init__.py
notifications_sender/send_notifications.py
notifications_sender-0.7.0.dist-info/METADATA
notifications_sender-0.7.0.dist-info/WHEEL
notifications_sender-0.7.0.dist-info/RECORD
